tencdec.py
tencdec-0.0.1.dist-info/LICENSE.md
tencdec-0.0.1.dist-info/METADATA
tencdec-0.0.1.dist-info/WHEEL
tencdec-0.0.1.dist-info/top_level.txt
tencdec-0.0.1.dist-info/RECORD
