Metadata-Version: 2.1
Name: tencdec
Version: 0.0.1
Summary: A number array to/from bytes high performance encoder/decoder.
Author-email: Facundo Batista <facundo@taniquetil.com.ar>
Project-URL: Homepage, https://github.com/facundobatista/tencdec
Project-URL: Bug Tracker, https://github.com/facundobatista/tencdec/issues
Classifier: Programming Language :: Python :: 3
Classifier: License :: OSI Approved :: GNU Lesser General Public License v2 or later (LGPLv2+)
Classifier: Operating System :: OS Independent
Requires-Python: >=3
License-File: LICENSE.md
